cwz/__init__.py
cwz/activity_from_fs.py
cwz/ci_build_metrics.py
cwz/cmk_components.py
cwz/py.typed
cwz/gerrit_utils/__init__.py
cwz/gerrit_utils/client.py
cwz/jenkins_utils/__init__.py
cwz/jenkins_utils/client.py
cmk_werk_zeug-0.1.5.dist-info/METADATA
cmk_werk_zeug-0.1.5.dist-info/WHEEL
cmk_werk_zeug-0.1.5.dist-info/entry_points.txt
cmk_werk_zeug-0.1.5.dist-info/licenses/LICENSE
cmk_werk_zeug-0.1.5.dist-info/RECORD
