Metadata-Version: 2.4
Name: cmk-werk-zeug
Version: 0.1.5
Summary: cmk-werk-zeug
Author-email: Benedikt Seidl <benedikt.seidl@checkmk.com>, Frans Fürst <frans.fuerst@checkmk.com>
License-File: LICENSE
Requires-Python: <4,>=3.12
Requires-Dist: aiohttp>=3.13.3
Requires-Dist: psycopg2-binary>=2.9.11
Requires-Dist: pydantic>=2
Requires-Dist: python-jenkins>=1.8.3
Requires-Dist: pyyaml>=6.0.3
Requires-Dist: sqlalchemy>=2.0.45
Requires-Dist: textual>=7.3.0
Requires-Dist: trickkiste>=0.3.4
